{"title":"JS数组扁平化方法总结","slug":"198","date":"2022-03-06T08:51:13.000Z","updated":"2022-07-21T08:46:19.518Z","comments":true,"path":"api/articles/198.json","excerpt":null,"covers":null,"content":"<figure class=\"highlight js\"><table><tr><td class=\"gutter\"><pre><span class=\"line\">1</span><br></pre></td><td class=\"code\"><pre><span class=\"line\"><span class=\"keyword\">let</span> ary = [<span class=\"number\">1</span>, [<span class=\"number\">2</span>, [<span class=\"number\">3</span>, [<span class=\"number\">4</span>, <span class=\"number\">5</span>]]], <span class=\"number\">6</span>];</span><br></pre></td></tr></table></figure>\n<p>常用：</p>\n<p>第一种：</p>\n<figure class=\"highlight js\"><table><tr><td class=\"gutter\"><pre><span class=\"line\">1</span><br></pre></td><td class=\"code\"><pre><span class=\"line\">arr_flat = arr.flat(<span class=\"literal\">Infinity</span>);</span><br></pre></td></tr></table></figure>\n<p>第二种：<strong>扩展运算符</strong></p>\n<figure class=\"highlight js\"><table><tr><td class=\"gutter\"><pre><span class=\"line\">1</span><br><span class=\"line\">2</span><br><span class=\"line\">3</span><br></pre></td><td class=\"code\"><pre><span class=\"line\"><span class=\"keyword\">while</span> (ary.some(<span class=\"built_in\">Array</span>.isArray)) &#123;</span><br><span class=\"line\">\tary = [].concat(...ary);</span><br><span class=\"line\">&#125;</span><br></pre></td></tr></table></figure>\n<p>第三种：</p>\n<figure class=\"highlight js\"><table><tr><td class=\"gutter\"><pre><span class=\"line\">1</span><br></pre></td><td class=\"code\"><pre><span class=\"line\">ary = str.replace(<span class=\"regexp\">/(\\[\\]))/g</span>, <span class=\"string\">&#x27;&#x27;</span>).split(<span class=\"string\">&#x27;,&#x27;</span>);</span><br></pre></td></tr></table></figure>\n","more":"<figure class=\"highlight js\"><table><tr><td class=\"gutter\"><pre><span class=\"line\">1</span><br></pre></td><td class=\"code\"><pre><span class=\"line\"><span class=\"keyword\">let</span> ary = [<span class=\"number\">1</span>, [<span class=\"number\">2</span>, [<span class=\"number\">3</span>, [<span class=\"number\">4</span>, <span class=\"number\">5</span>]]], <span class=\"number\">6</span>];</span><br></pre></td></tr></table></figure>\n<p>常用：</p>\n<p>第一种：</p>\n<figure class=\"highlight js\"><table><tr><td class=\"gutter\"><pre><span class=\"line\">1</span><br></pre></td><td class=\"code\"><pre><span class=\"line\">arr_flat = arr.flat(<span class=\"literal\">Infinity</span>);</span><br></pre></td></tr></table></figure>\n<p>第二种：<strong>扩展运算符</strong></p>\n<figure class=\"highlight js\"><table><tr><td class=\"gutter\"><pre><span class=\"line\">1</span><br><span class=\"line\">2</span><br><span class=\"line\">3</span><br></pre></td><td class=\"code\"><pre><span class=\"line\"><span class=\"keyword\">while</span> (ary.some(<span class=\"built_in\">Array</span>.isArray)) &#123;</span><br><span class=\"line\">\tary = [].concat(...ary);</span><br><span class=\"line\">&#125;</span><br></pre></td></tr></table></figure>\n<p>第三种：</p>\n<figure class=\"highlight js\"><table><tr><td class=\"gutter\"><pre><span class=\"line\">1</span><br></pre></td><td class=\"code\"><pre><span class=\"line\">ary = str.replace(<span class=\"regexp\">/(\\[\\]))/g</span>, <span class=\"string\">&#x27;&#x27;</span>).split(<span class=\"string\">&#x27;,&#x27;</span>);</span><br></pre></td></tr></table></figure>\n","categories":[{"name":"JavaScript","path":"api/categories/JavaScript.json"}],"tags":[{"name":"JavaScript","path":"api/tags/JavaScript.json"}]}