{"title":"element input 限制值不为负数且类型为数字","slug":"205","date":"2022-07-03T07:04:58.000Z","updated":"2022-07-21T08:45:56.846Z","comments":true,"path":"api/articles/205.json","excerpt":null,"covers":null,"content":"<figure class=\"highlight html\"><table><tr><td class=\"gutter\"><pre><span class=\"line\">1</span><br><span class=\"line\">2</span><br><span class=\"line\">3</span><br><span class=\"line\">4</span><br><span class=\"line\">5</span><br><span class=\"line\">6</span><br><span class=\"line\">7</span><br></pre></td><td class=\"code\"><pre><span class=\"line\"><span class=\"tag\">&lt;<span class=\"name\">el-input</span></span></span><br><span class=\"line\"><span class=\"tag\">  <span class=\"attr\">v-model</span>=<span class=\"string\">&quot;formData.bid&quot;</span></span></span><br><span class=\"line\"><span class=\"tag\">  <span class=\"attr\">clearable</span></span></span><br><span class=\"line\"><span class=\"tag\">  <span class=\"attr\">style</span>=<span class=\"string\">&quot;width:180px;&quot;</span></span></span><br><span class=\"line\"><span class=\"tag\">  <span class=\"attr\">oninput</span>=<span class=\"string\">&quot;value=value.replace(/[^0-9.]/g,&#x27;&#x27;)&quot;</span></span></span><br><span class=\"line\"><span class=\"tag\">&gt;</span></span><br><span class=\"line\"><span class=\"tag\">&lt;/<span class=\"name\">el-input</span>&gt;</span></span><br></pre></td></tr></table></figure>\n<p>只允许数字和英文逗号的正则表达式</p>\n<figure class=\"highlight js\"><table><tr><td class=\"gutter\"><pre><span class=\"line\">1</span><br></pre></td><td class=\"code\"><pre><span class=\"line\">/^[-,<span class=\"number\">0</span>-<span class=\"number\">9</span>]+$/.test(val)</span><br></pre></td></tr></table></figure>\n<p>仅可输入中文英文数字以及英文逗号</p>\n<figure class=\"highlight js\"><table><tr><td class=\"gutter\"><pre><span class=\"line\">1</span><br></pre></td><td class=\"code\"><pre><span class=\"line\">/^[a-zA-Z0-<span class=\"number\">9</span>,\\u4e00-\\u9fa5]+$/</span><br></pre></td></tr></table></figure>\n<p>2.el-input-number 整数取值</p>\n<figure class=\"highlight html\"><table><tr><td class=\"gutter\"><pre><span class=\"line\">1</span><br><span class=\"line\">2</span><br></pre></td><td class=\"code\"><pre><span class=\"line\"><span class=\"tag\">&lt;<span class=\"name\">el-input-number</span> <span class=\"attr\">v-model</span>=<span class=\"string\">&quot;row.columnWidth&quot;</span> <span class=\"attr\">:disabled</span>=<span class=\"string\">&quot;dialogVO.action == 0&quot;</span> <span class=\"attr\">controls-position</span>=<span class=\"string\">&quot;right&quot;</span> <span class=\"attr\">:precision</span>=<span class=\"string\">&quot;0&quot;</span>  <span class=\"attr\">:min</span>=<span class=\"string\">&quot;0&quot;</span> <span class=\"attr\">:max</span>=<span class=\"string\">&quot;800&quot;</span>&gt;</span><span class=\"tag\">&lt;/<span class=\"name\">el-input-number</span>&gt;</span></span><br><span class=\"line\">// :precision=&quot;0&quot;  element-ui自带属性</span><br></pre></td></tr></table></figure>\n","more":"<figure class=\"highlight html\"><table><tr><td class=\"gutter\"><pre><span class=\"line\">1</span><br><span class=\"line\">2</span><br><span class=\"line\">3</span><br><span class=\"line\">4</span><br><span class=\"line\">5</span><br><span class=\"line\">6</span><br><span class=\"line\">7</span><br></pre></td><td class=\"code\"><pre><span class=\"line\"><span class=\"tag\">&lt;<span class=\"name\">el-input</span></span></span><br><span class=\"line\"><span class=\"tag\">  <span class=\"attr\">v-model</span>=<span class=\"string\">&quot;formData.bid&quot;</span></span></span><br><span class=\"line\"><span class=\"tag\">  <span class=\"attr\">clearable</span></span></span><br><span class=\"line\"><span class=\"tag\">  <span class=\"attr\">style</span>=<span class=\"string\">&quot;width:180px;&quot;</span></span></span><br><span class=\"line\"><span class=\"tag\">  <span class=\"attr\">oninput</span>=<span class=\"string\">&quot;value=value.replace(/[^0-9.]/g,&#x27;&#x27;)&quot;</span></span></span><br><span class=\"line\"><span class=\"tag\">&gt;</span></span><br><span class=\"line\"><span class=\"tag\">&lt;/<span class=\"name\">el-input</span>&gt;</span></span><br></pre></td></tr></table></figure>\n<p>只允许数字和英文逗号的正则表达式</p>\n<figure class=\"highlight js\"><table><tr><td class=\"gutter\"><pre><span class=\"line\">1</span><br></pre></td><td class=\"code\"><pre><span class=\"line\">/^[-,<span class=\"number\">0</span>-<span class=\"number\">9</span>]+$/.test(val)</span><br></pre></td></tr></table></figure>\n<p>仅可输入中文英文数字以及英文逗号</p>\n<figure class=\"highlight js\"><table><tr><td class=\"gutter\"><pre><span class=\"line\">1</span><br></pre></td><td class=\"code\"><pre><span class=\"line\">/^[a-zA-Z0-<span class=\"number\">9</span>,\\u4e00-\\u9fa5]+$/</span><br></pre></td></tr></table></figure>\n<p>2.el-input-number 整数取值</p>\n<figure class=\"highlight html\"><table><tr><td class=\"gutter\"><pre><span class=\"line\">1</span><br><span class=\"line\">2</span><br></pre></td><td class=\"code\"><pre><span class=\"line\"><span class=\"tag\">&lt;<span class=\"name\">el-input-number</span> <span class=\"attr\">v-model</span>=<span class=\"string\">&quot;row.columnWidth&quot;</span> <span class=\"attr\">:disabled</span>=<span class=\"string\">&quot;dialogVO.action == 0&quot;</span> <span class=\"attr\">controls-position</span>=<span class=\"string\">&quot;right&quot;</span> <span class=\"attr\">:precision</span>=<span class=\"string\">&quot;0&quot;</span>  <span class=\"attr\">:min</span>=<span class=\"string\">&quot;0&quot;</span> <span class=\"attr\">:max</span>=<span class=\"string\">&quot;800&quot;</span>&gt;</span><span class=\"tag\">&lt;/<span class=\"name\">el-input-number</span>&gt;</span></span><br><span class=\"line\">// :precision=&quot;0&quot;  element-ui自带属性</span><br></pre></td></tr></table></figure>\n","categories":[{"name":"Element","path":"api/categories/Element.json"}],"tags":[{"name":"Element","path":"api/tags/Element.json"}]}