{"name":"科学上网","postlist":[{"title":"如何使用手机（安卓）进行科学访问外网 2020最新教程","slug":"123","date":"2020-09-25T03:40:36.000Z","updated":"2022-07-07T06:25:18.406Z","comments":true,"path":"api/articles/123.json","excerpt":null,"keywords":null,"cover":"https://qny.aqingya.cn/img/wzgimage (1).png","content":null,"raw":null,"categories":[{"name":"闻所未闻","path":"api/categories/闻所未闻.json"}],"tags":[{"name":"安卓","path":"api/tags/安卓.json"},{"name":"科学上网","path":"api/tags/科学上网.json"},{"name":"访问外网","path":"api/tags/访问外网.json"}]}]}